{
  "apiVersion": "appuio.io/v1",
  "kind": "ZoneList",
  "items": [
    {
      "apiVersion": "appuio.io/v1",
      "data": {
        "cloudProvider": {
          "name": "cloudscale.ch",
          "region": "Lupfig (AG)",
          "zones": ["lpg1"]
        },
        "cname": "cname.cloudscale-lpg-0.appuio.cloud",
        "defaultAppDomain": "apps.cloudscale-lpg-0.appuio.cloud",
        "displayName": "cloudscale.ch LPG 0",
        "features": {
          "kubernetesVersion": "1.21",
          "openshiftVersion": "4.8",
          "sdnPlugin": "OVN-Kubernetes"
        },
        "gatewayIPs": ["185.98.123.122"],
        "urls": {
          "console": "https://console.cloudscale-lpg-0.appuio.cloud/",
          "kubernetesAPI": "https://api.cloudscale-lpg-0.appuio.cloud:6443/",
          "logging": "https://logging.cloudscale-lpg-0.appuio.cloud/",
          "registry": "https://registry.cloudscale-lpg-0.appuio.cloud"
        }
      },
      "kind": "Zone"
    },
    {
      "apiVersion": "appuio.io/v1",
      "data": {
        "cloudProvider": {
          "name": "cloudscale.ch",
          "region": "Lupfig (AG)",
          "zones": ["lpg2"]
        },
        "cname": "cname.cloudscale-lpg-2.appuio.cloud",
        "defaultAppDomain": "apps.cloudscale-lpg-2.appuio.cloud",
        "displayName": "cloudscale.ch LPG 2",
        "features": {
          "kubernetesVersion": "1.21",
          "openshiftVersion": "4.8",
          "sdnPlugin": "OVN-Kubernetes"
        },
        "gatewayIPs": ["185.98.123.122"],
        "urls": {
          "console": "https://console.cloudscale-lpg-2.appuio.cloud/",
          "kubernetesAPI": "https://api.cloudscale-lpg-2.appuio.cloud:6443/",
          "logging": "https://logging.cloudscale-lpg-2.appuio.cloud/",
          "registry": "https://registry.cloudscale-lpg-2.appuio.cloud"
        }
      },
      "kind": "Zone"
    }
  ],
  "metadata": {
    "continue": "",
    "resourceVersion": ""
  }
}
